{
  "BackgroundColor": "(100,100,100)",
  "Menus": [
    {
      "name": "Multimedia",
      "color": "(255,255,176)",
      "fontColor": "(0,0,0)",
      "entries": [
        {
          "name": "Kodi",
          "color": "(255,255,176)",
          "fontColor": "(0,0,0)",
          "return": 64
        },
        {
          "name": "VLC",
          "color": "(255,255,176)",
          "fontColor": "(0,0,0)",
          "return": 65
        }
      ]
    },
    {
      "name": "Games",
      "color": "(204,236,239)",
      "fontColor": "(0,0,0)",
      "entries": [
        {
          "name": "Nes",
          "color": "(255,255,176)",
          "fontColor": "(0,0,0)",
          "return": 66
        },
        {
          "name": "Snes",
          "color": "(255,255,176)",
          "fontColor": "(0,0,0)",
          "return": 67
        }
      ]
    },
    {
      "name": "Other",
      "color": "(224,243,176)",
      "fontColor": "(0,0,0)",
      "entries": [
        {
          "name": "Firefox",
          "color": "(255,255,176)",
          "fontColor": "(0,0,0)",
          "return": 68
        }
      ]
    }
  ]
}